odoo8_addon_stock_auto_move-8.0.1.0.0.99.dev20-nspkg.pth
odoo_addons/stock_auto_move/README.rst
odoo_addons/stock_auto_move/__init__.py
odoo_addons/stock_auto_move/__openerp__.py
odoo_addons/stock_auto_move/data/stock_auto_move_data.xml
odoo_addons/stock_auto_move/demo/stock_auto_move_demo.xml
odoo_addons/stock_auto_move/i18n/ca.po
odoo_addons/stock_auto_move/i18n/de.po
odoo_addons/stock_auto_move/i18n/es.po
odoo_addons/stock_auto_move/i18n/es_AR.po
odoo_addons/stock_auto_move/i18n/es_MX.po
odoo_addons/stock_auto_move/i18n/fi.po
odoo_addons/stock_auto_move/i18n/fr.po
odoo_addons/stock_auto_move/i18n/hr.po
odoo_addons/stock_auto_move/i18n/it.po
odoo_addons/stock_auto_move/i18n/pt.po
odoo_addons/stock_auto_move/i18n/pt_BR.po
odoo_addons/stock_auto_move/i18n/pt_PT.po
odoo_addons/stock_auto_move/i18n/ro.po
odoo_addons/stock_auto_move/i18n/sk.po
odoo_addons/stock_auto_move/i18n/sl.po
odoo_addons/stock_auto_move/i18n/stock_auto_move.pot
odoo_addons/stock_auto_move/i18n/tr.po
odoo_addons/stock_auto_move/i18n/tr_TR.po
odoo_addons/stock_auto_move/i18n/zh_CN.po
odoo_addons/stock_auto_move/models/__init__.py
odoo_addons/stock_auto_move/models/stock_auto_move.py
odoo_addons/stock_auto_move/static/description/icon.png
odoo_addons/stock_auto_move/tests/__init__.py
odoo_addons/stock_auto_move/tests/test_stock_auto_move.py
odoo_addons/stock_auto_move/views/stock_auto_move_view.xml
odoo8_addon_stock_auto_move-8.0.1.0.0.99.dev20.dist-info/METADATA
odoo8_addon_stock_auto_move-8.0.1.0.0.99.dev20.dist-info/WHEEL
odoo8_addon_stock_auto_move-8.0.1.0.0.99.dev20.dist-info/namespace_packages.txt
odoo8_addon_stock_auto_move-8.0.1.0.0.99.dev20.dist-info/top_level.txt
odoo8_addon_stock_auto_move-8.0.1.0.0.99.dev20.dist-info/RECORD
